pylibrespot_java/__init__.py
pylibrespot_java-0.1.1.dist-info/LICENSE.txt
pylibrespot_java-0.1.1.dist-info/METADATA
pylibrespot_java-0.1.1.dist-info/WHEEL
pylibrespot_java-0.1.1.dist-info/top_level.txt
pylibrespot_java-0.1.1.dist-info/RECORD
