Metadata-Version: 2.1
Name: pylibrespot-java
Version: 0.1.1
Summary: Python Interface for librespot-java
Home-page: http://github.com/uvjustin/pylibrespot-java/
Author: Justin Wong
Author-email: 46082645+uvjustin@users.noreply.github.com
Platform: any
Classifier: Programming Language :: Python
Classifier: Development Status :: 4 - Beta
Classifier: Natural Language :: English
Classifier: Environment :: Web Environment
Classifier: Intended Audience :: Developers
Classifier: License :: OSI Approved :: MIT License
Classifier: Operating System :: OS Independent
Classifier: Topic :: Software Development :: Libraries :: Python Modules
License-File: LICENSE.txt
